MANIFEST.in
README.txt
setup.py
atreal/__init__.py
atreal.richfile.qualifier.egg-info/PKG-INFO
atreal.richfile.qualifier.egg-info/SOURCES.txt
atreal.richfile.qualifier.egg-info/dependency_links.txt
atreal.richfile.qualifier.egg-info/entry_points.txt
atreal.richfile.qualifier.egg-info/namespace_packages.txt
atreal.richfile.qualifier.egg-info/not-zip-safe
atreal.richfile.qualifier.egg-info/requires.txt
atreal.richfile.qualifier.egg-info/top_level.txt
atreal/richfile/__init__.py
atreal/richfile/qualifier/__init__.py
atreal/richfile/qualifier/common.py
atreal/richfile/qualifier/configure.zcml
atreal/richfile/qualifier/events.py
atreal/richfile/qualifier/interfaces.py
atreal/richfile/qualifier/patch.py
atreal/richfile/qualifier/qualifier.py
atreal/richfile/qualifier/registry.py
atreal/richfile/qualifier/tests.py
atreal/richfile/qualifier/upgrades.py
atreal/richfile/qualifier/utility.py
atreal/richfile/qualifier/browser/__init__.py
atreal/richfile/qualifier/browser/common.css
atreal/richfile/qualifier/browser/common.kss
atreal/richfile/qualifier/browser/configure.zcml
atreal/richfile/qualifier/browser/controlpanel.pt
atreal/richfile/qualifier/browser/controlpanel.py
atreal/richfile/qualifier/browser/controls.pt
atreal/richfile/qualifier/browser/richfile_viewlet.pt
atreal/richfile/qualifier/browser/viewlets.py
atreal/richfile/qualifier/browser/images/controls-actions_mapping.gif
atreal/richfile/qualifier/browser/images/controls-actions_mapping.png
atreal/richfile/qualifier/browser/images/filequalifier_icon.png
atreal/richfile/qualifier/locales/atreal.richfile.qualifier.pot
atreal/richfile/qualifier/locales/fr/LC_MESSAGES/atreal.richfile.qualifier.mo
atreal/richfile/qualifier/locales/fr/LC_MESSAGES/atreal.richfile.qualifier.po
atreal/richfile/qualifier/profiles/default/actionicons.xml
atreal/richfile/qualifier/profiles/default/browserlayer.xml
atreal/richfile/qualifier/profiles/default/componentregistry.xml
atreal/richfile/qualifier/profiles/default/controlpanel.xml
atreal/richfile/qualifier/profiles/default/cssregistry.xml
atreal/richfile/qualifier/profiles/default/kssregistry.xml
atreal/richfile/qualifier/profiles/default/metadata.xml
docs/HISTORY.txt
docs/INSTALL.txt
docs/LICENSE.GPL
docs/LICENSE.txt