Metadata-Version: 1.0
Name: atreal.richfile.qualifier
Version: 1.1.1
Summary: System to enrich a file content type in Plone with a marker interface regarding its mimetype.
Home-page: http://svn.plone.org/svn/collective/atreal.richfile.qualifier/
Author: atReal
Author-email: contact@atreal.fr
License: GPL
Keywords: plone atreal richfile qualifier
Platform: UNKNOWN
Classifier: Framework :: Plone
Classifier: Programming Language :: Python
Classifier: Topic :: Software Development :: Libraries :: Python Modules
